sklm/__init__.py
sklm/examples.py
sklm/transforms.py
SKLMisc-0.0.1.dist-info/LICENSE
SKLMisc-0.0.1.dist-info/METADATA
SKLMisc-0.0.1.dist-info/WHEEL
SKLMisc-0.0.1.dist-info/top_level.txt
SKLMisc-0.0.1.dist-info/RECORD
