Metadata-Version: 2.1
Name: SKLMisc
Version: 0.0.1
Summary: Miscellaneous code associated with SKLearn.
Author-email: Galen Seilis <galen.seilis@seilis.ca>
Project-URL: Homepage, https://github.com/galenseilis/Scikit-Learn-Miscellaneous
Project-URL: Bug Tracker, https://github.com/galenseilis/Scikit-Learn-Miscellaneous/issues
Classifier: Programming Language :: Python :: 3
Classifier: License :: OSI Approved :: MIT License
Classifier: Operating System :: OS Independent
Requires-Python: >=3.7
License-File: LICENSE
